duper/.DS_Store
duper/__about__.py
duper/__init__.py
duper/_msg.py
duper/constants.py
duper/fastast.py
duper/factories/__init__.py
duper/factories/ast.py
duper/factories/recursive.py
duper/factories/runtime.py
duper/factories/tlv.py
duper-0.0.6.dist-info/METADATA
duper-0.0.6.dist-info/WHEEL
duper-0.0.6.dist-info/licenses/LICENSE
duper-0.0.6.dist-info/RECORD
