Metadata-Version: 2.1
Name: duper
Version: 0.0.6
Project-URL: Documentation, https://github.com/Bobronium/duper#readme
Project-URL: Issues, https://github.com/Bobronium/duper/issues
Project-URL: Source, https://github.com/Bobronium/duper
Author-email: Bobronium <appkiller16@gmail.com>
License-File: LICENSE
Classifier: Development Status :: 4 - Beta
Classifier: Programming Language :: Python
Classifier: Programming Language :: Python :: 3.7
Classifier: Programming Language :: Python :: 3.8
Classifier: Programming Language :: Python :: 3.9
Classifier: Programming Language :: Python :: 3.10
Classifier: Programming Language :: Python :: 3.11
Classifier: Programming Language :: Python :: Implementation :: CPython
Classifier: Programming Language :: Python :: Implementation :: PyPy
Requires-Python: >=3.7
Requires-Dist: mypy-extensions
Requires-Dist: typing-extensions; python_version < '3.11'
Provides-Extra: benchmark
Requires-Dist: dill; extra == 'benchmark'
Requires-Dist: ipython; extra == 'benchmark'
Requires-Dist: orjson; extra == 'benchmark'
Requires-Dist: pyinstrument; extra == 'benchmark'
Provides-Extra: debugging
Requires-Dist: ipython; extra == 'debugging'
Provides-Extra: dev
Requires-Dist: astpretty; extra == 'dev'
Requires-Dist: bytecode; extra == 'dev'
Provides-Extra: profiling
Requires-Dist: pyinstrument; extra == 'profiling'
Provides-Extra: style
Requires-Dist: black; extra == 'style'
Requires-Dist: isort; extra == 'style'
Requires-Dist: pyupgrade; extra == 'style'
Requires-Dist: ruff; extra == 'style'
Provides-Extra: testing
Requires-Dist: pytest; extra == 'testing'
Requires-Dist: pytest-cov; extra == 'testing'
Provides-Extra: typing
Requires-Dist: mypy; extra == 'typing'
